rtp/io.cpython-311-s390x-linux-gnu.so
rtp_io-1.0.3.dist-info/METADATA
rtp_io-1.0.3.dist-info/WHEEL
rtp_io-1.0.3.dist-info/top_level.txt
rtp_io-1.0.3.dist-info/RECORD
rtp_io-1.0.3.dist-info/licenses/LICENSE
