Metadata-Version: 2.4
Name: rtp.io
Version: 1.0.3
Summary: Fast RTPProxy-like RTP handling/processing engine.
Classifier: Programming Language :: Python :: 3
Classifier: Programming Language :: C
License-File: LICENSE
Dynamic: classifier
Dynamic: description
Dynamic: description-content-type
Dynamic: license-file
Dynamic: summary
